sub_byte/__init__.py
sub_byte/factories.py
sub_byte/py.typed
sub_byte-0.0.7.dist-info/METADATA
sub_byte-0.0.7.dist-info/WHEEL
sub_byte-0.0.7.dist-info/licenses/LICENSE.md
sub_byte-0.0.7.dist-info/RECORD
