Metadata-Version: 2.4
Name: sub-byte
Version: 0.0.7
Summary: Encodes and decodes sequences of unsigned integers with known widths (and sequences of symbols from finite sets). 
Project-URL: Homepage, https://github.com/NumberzGame/sub_byte
Project-URL: Bug Tracker, https://github.com/NumberzGame/sub_byte/issues
Author-email: James Parrott <james.parrott@proton.me>
License: MIT License
License-File: LICENSE.md
Keywords: Encoders,Serialization
Classifier: Programming Language :: Python
Requires-Python: >=3.12
Requires-Dist: more-itertools
Provides-Extra: mypy
Requires-Dist: mypy; extra == 'mypy'
Provides-Extra: test
Requires-Dist: hypothesis; extra == 'test'
Requires-Dist: pytest; extra == 'test'
